ptcfextract/__init__.py
ptcfextract/cli.py
ptcfextract/core.py
ptcfextract-0.1.0.dist-info/licenses/LICENSE
ptcfextract-0.1.0.dist-info/METADATA
ptcfextract-0.1.0.dist-info/WHEEL
ptcfextract-0.1.0.dist-info/entry_points.txt
ptcfextract-0.1.0.dist-info/top_level.txt
ptcfextract-0.1.0.dist-info/RECORD
