Metadata-Version: 2.4
Name: ptcfextract
Version: 0.1.0
Summary: Compute per-point linearity/planarity/scattering features for LAS/LAZ point clouds with LAS ExtraBytes export and RGB visualization outputs.
Author: Kenneth Kwabena Kenney
License: MIT License
Keywords: point-cloud,lidar,las,laz,open3d,features,geometry,linearity,planarity,scattering
Classifier: Programming Language :: Python :: 3
Classifier: License :: OSI Approved :: MIT License
Classifier: Operating System :: OS Independent
Requires-Python: >=3.8
License-File: LICENSE
Requires-Dist: numpy>=1.21
Requires-Dist: scipy>=1.8
Requires-Dist: laspy>=2.4
Requires-Dist: lazrs>=0.5
Requires-Dist: open3d>=0.17
Requires-Dist: opencv-python>=4.7
Provides-Extra: laz
Requires-Dist: lazrs>=0.5; extra == "laz"
Dynamic: license-file
